metalpy/__init__.py
metalpy/_version.py
metalpy/version.py
metalpy/aero/__init__.py
metalpy/aero/routes/__init__.py
metalpy/aero/routes/aerial_survey/__init__.py
metalpy/aero/routes/aerial_survey/aerial_survey.py
metalpy/aero/routes/aerial_survey/aerial_survey_line.py
metalpy/aero/routes/aerial_survey/aerial_survey_lines.py
metalpy/aero/routes/aerial_survey/aerial_survey_point.py
metalpy/aero/routes/flight_planar/__init__.py
metalpy/aero/routes/flight_planar/flight_planar.py
metalpy/aero/utils/__init__.py
metalpy/aero/utils/exif.py
metalpy/aero/utils/line_analysis.py
metalpy/carto/basemap/__init__.py
metalpy/carto/basemap/constants.py
metalpy/carto/basemap/gdal_helper.py
metalpy/carto/basemap/geo_image.py
metalpy/carto/basemap/geo_image_ref_system.py
metalpy/carto/basemap/map_downloader.py
metalpy/carto/basemap/sources/__init__.py
metalpy/carto/basemap/sources/amap_source.py
metalpy/carto/basemap/sources/google_map_source.py
metalpy/carto/basemap/sources/simple_tile_locator.py
metalpy/carto/basemap/sources/simple_tile_map_source.py
metalpy/carto/basemap/sources/tile_locator.py
metalpy/carto/basemap/sources/tile_map_source.py
metalpy/carto/basemap/sources/wayback_source.py
metalpy/carto/coords/__init__.py
metalpy/carto/coords/chs_coords.py
metalpy/carto/coords/coordinates.py
metalpy/carto/pyvista/crs.py
metalpy/carto/utils/crs.py
metalpy/carto/utils/mpl.py
metalpy/carto/utils/pyvista_turtle.py
metalpy/mepa/__init__.py
metalpy/mepa/dask_executor.py
metalpy/mepa/dask_helper.py
metalpy/mepa/executor.py
metalpy/mepa/lazy_evaluator.py
metalpy/mepa/linear_executor.py
metalpy/mepa/parallel_progress.py
metalpy/mepa/pool_executor.py
metalpy/mepa/process_executor.py
metalpy/mepa/queue_like_worker_context.py
metalpy/mepa/shared_array.py
metalpy/mepa/sub_executor.py
metalpy/mepa/task_allocator.py
metalpy/mepa/thread_executor.py
metalpy/mepa/utils.py
metalpy/mepa/worker.py
metalpy/mepa/worker_context.py
metalpy/mepa/tests/test_allocator.py
metalpy/mexin/__init__.py
metalpy-0.2.0.dist-info/LICENSE.txt
metalpy-0.2.0.dist-info/METADATA
metalpy-0.2.0.dist-info/WHEEL
metalpy-0.2.0.dist-info/top_level.txt
metalpy-0.2.0.dist-info/RECORD
