Metadata-Version: 2.1
Name: metalpy
Version: 0.2.0
Summary: Essential tools and libraries for SimPEG and related workflows.
Author-email: yanang007 <yanang007@gmail.com>
License: MIT License
Classifier: Programming Language :: Python :: 3
Classifier: Operating System :: OS Independent
Classifier: License :: OSI Approved :: MIT License
Requires-Python: >=3.9
License-File: LICENSE.txt
Provides-Extra: aero
Requires-Dist: piexif ; extra == 'aero'
Provides-Extra: build
Requires-Dist: tomli ; extra == 'build'
Requires-Dist: build ; extra == 'build'
Provides-Extra: carto
Requires-Dist: numpy ; extra == 'carto'
Requires-Dist: pillow ; extra == 'carto'
Requires-Dist: imageio ; extra == 'carto'
Requires-Dist: requests ; extra == 'carto'
Requires-Dist: pyproj ; extra == 'carto'
Requires-Dist: rasterio ; extra == 'carto'
Requires-Dist: affine ; extra == 'carto'
Provides-Extra: complete
Requires-Dist: metalpy[carto,mepa,mexin,scab,utils] ; extra == 'complete'
Provides-Extra: dev
Requires-Dist: metalpy[build,complete,docs,tests] ; extra == 'dev'
Requires-Dist: nox ; extra == 'dev'
Requires-Dist: versioningit ; extra == 'dev'
Provides-Extra: docs
Requires-Dist: sphinx ; extra == 'docs'
Provides-Extra: mepa
Requires-Dist: loky ; extra == 'mepa'
Requires-Dist: distributed ; extra == 'mepa'
Requires-Dist: psutil ; extra == 'mepa'
Provides-Extra: mexin
Provides-Extra: pure
Provides-Extra: scab
Requires-Dist: metalpy[mepa,mexin,utils] ; extra == 'scab'
Requires-Dist: SimPEG <0.22,>=0.20 ; extra == 'scab'
Requires-Dist: discretize >=0.8.3 ; extra == 'scab'
Requires-Dist: numpy <2 ; extra == 'scab'
Requires-Dist: pandas ; extra == 'scab'
Requires-Dist: scipy ; extra == 'scab'
Requires-Dist: scikit-learn ; extra == 'scab'
Requires-Dist: pyvista >=0.43.1 ; extra == 'scab'
Requires-Dist: matplotlib ; extra == 'scab'
Requires-Dist: colour ; extra == 'scab'
Requires-Dist: taichi >=1.7.0 ; extra == 'scab'
Requires-Dist: properties ; extra == 'scab'
Requires-Dist: pympler ; extra == 'scab'
Requires-Dist: psutil ; extra == 'scab'
Requires-Dist: blosc2 >=0.4.0 ; extra == 'scab'
Requires-Dist: tqdm ; extra == 'scab'
Provides-Extra: tests
Requires-Dist: metalpy[complete] ; extra == 'tests'
Requires-Dist: pytest ; extra == 'tests'
Provides-Extra: utils
Requires-Dist: numpy ; extra == 'utils'
Requires-Dist: blosc2 >=0.4.0 ; extra == 'utils'
Requires-Dist: cloudpickle ; extra == 'utils'
Requires-Dist: tqdm ; extra == 'utils'
Requires-Dist: typing-extensions ; extra == 'utils'
